odoo/addons/stock_move_line_reference_link/README.rst
odoo/addons/stock_move_line_reference_link/__init__.py
odoo/addons/stock_move_line_reference_link/__manifest__.py
odoo/addons/stock_move_line_reference_link/i18n/it.po
odoo/addons/stock_move_line_reference_link/i18n/stock_move_line_reference_link.pot
odoo/addons/stock_move_line_reference_link/models/__init__.py
odoo/addons/stock_move_line_reference_link/models/stock_move_line.py
odoo/addons/stock_move_line_reference_link/readme/CONTRIBUTORS.md
odoo/addons/stock_move_line_reference_link/readme/DESCRIPTION.md
odoo/addons/stock_move_line_reference_link/static/description/icon.png
odoo/addons/stock_move_line_reference_link/static/description/index.html
odoo/addons/stock_move_line_reference_link/tests/__init__.py
odoo/addons/stock_move_line_reference_link/tests/test_move_line.py
odoo/addons/stock_move_line_reference_link/views/move_line_views.xml
odoo_addon_stock_move_line_reference_link-18.0.1.0.0.2.dist-info/METADATA
odoo_addon_stock_move_line_reference_link-18.0.1.0.0.2.dist-info/WHEEL
odoo_addon_stock_move_line_reference_link-18.0.1.0.0.2.dist-info/top_level.txt
odoo_addon_stock_move_line_reference_link-18.0.1.0.0.2.dist-info/RECORD
